mongoengine_plus/__init__.py
mongoengine_plus/version.py
mongoengine_plus/aio/__init__.py
mongoengine_plus/aio/async_document.py
mongoengine_plus/aio/async_query_set.py
mongoengine_plus/aio/async_signals.py
mongoengine_plus/aio/utils.py
mongoengine_plus/models/__init__.py
mongoengine_plus/models/base.py
mongoengine_plus/models/event_handlers.py
mongoengine_plus/models/helpers.py
mongoengine_plus/types/__init__.py
mongoengine_plus/types/enum_field.py
mongoengine_plus/types/encrypted_string/__init__.py
mongoengine_plus/types/encrypted_string/base.py
mongoengine_plus/types/encrypted_string/exc.py
mongoengine_plus/types/encrypted_string/fields.py
mongoengine_plus-1.3.0.dist-info/licenses/LICENSE
tests/__init__.py
tests/conftest.py
tests/aio/__init__.py
tests/aio/cities.py
tests/aio/conftest.py
tests/aio/test_async_model.py
tests/aio/test_async_query_set.py
tests/aio/test_async_signals.py
tests/models/__init__.py
tests/models/test_base.py
tests/models/test_event_handlers.py
tests/models/test_helpers.py
tests/types/__init__.py
tests/types/test_encrypted_string.py
mongoengine_plus-1.3.0.dist-info/METADATA
mongoengine_plus-1.3.0.dist-info/WHEEL
mongoengine_plus-1.3.0.dist-info/top_level.txt
mongoengine_plus-1.3.0.dist-info/RECORD
