Metadata-Version: 2.4
Name: mongoengine-plus
Version: 1.3.0
Summary: Extras for mongoengine
Home-page: https://github.com/cuenca-mx/mongoengine-plus
Author: Cuenca
Author-email: dev@cuenca.com
Classifier: Programming Language :: Python :: 3.10
Classifier: Programming Language :: Python :: 3.11
Classifier: Programming Language :: Python :: 3.12
Classifier: Programming Language :: Python :: 3.13
Classifier: License :: OSI Approved :: MIT License
Classifier: Operating System :: OS Independent
Requires-Python: >=3.10
License-File: LICENSE
Requires-Dist: mongoengine>=0.29.1
Requires-Dist: dnspython>=2.7.0
Requires-Dist: pymongo<5.0.0,>=4.0.0
Requires-Dist: pymongocrypt<2.0.0,>=1.12.2
Requires-Dist: boto3<2.0.0,>=1.34.106
Requires-Dist: blinker<2.0.0,>=1.9.0
Dynamic: author
Dynamic: author-email
Dynamic: classifier
Dynamic: description
Dynamic: description-content-type
Dynamic: home-page
Dynamic: license-file
Dynamic: requires-dist
Dynamic: requires-python
Dynamic: summary
